audiovisualizer/__init__.py
audiovisualizer-1.0.2.dist-info/LICENSE.txt
audiovisualizer-1.0.2.dist-info/METADATA
audiovisualizer-1.0.2.dist-info/WHEEL
audiovisualizer-1.0.2.dist-info/entry_points.txt
audiovisualizer-1.0.2.dist-info/top_level.txt
audiovisualizer-1.0.2.dist-info/RECORD
