Metadata-Version: 2.1
Name: audiovisualizer
Version: 1.0.2
Summary: Visaualize audio stream in terminal
License: MIT License
Project-URL: Homepage, https://github.com/tracksuitdev/terminal-audio-visualizer
Project-URL: Source, https://github.com/tracksuitdev/terminal-audio-visualizer
Keywords: audio,visualize,stream,frames
Requires-Python: >=3.7
License-File: LICENSE.txt
Provides-Extra: run
Requires-Dist: pydub ; extra == 'run'
